backframe/__init__.py
backframe/py.typed
backframe-0.1.2.dist-info/LICENSE
backframe-0.1.2.dist-info/METADATA
backframe-0.1.2.dist-info/WHEEL
backframe-0.1.2.dist-info/RECORD
