Metadata-Version: 2.1
Name: backframe
Version: 0.1.2
Summary: Inspect the caller.
Home-page: https://github.com/bswck/backframe
License: MIT
Author: bswck
Author-email: bartoszpiotrslawecki@gmail.com
Requires-Python: >=3.8
Classifier: License :: OSI Approved :: MIT License
Classifier: Programming Language :: Python :: 3
Classifier: Programming Language :: Python :: 3.8
Classifier: Programming Language :: Python :: 3.9
Classifier: Programming Language :: Python :: 3.10
Classifier: Programming Language :: Python :: 3.11
Classifier: Programming Language :: Python :: 3.12
Project-URL: Coverage, https://coverage-badge.samuelcolvin.workers.dev/redirect/bswck/backframe
Project-URL: Documentation, https://backframe.readthedocs.io/en/latest/
Project-URL: Distribution, https://pypi.org/project/backframe/
Project-URL: Issues, https://github.com/bswck/backframe/issues
